NodeStickyLinks/__init__.py
NodeStickyLinks/drawsticky.py
NodeStickyLinks/run_drawsticky.py
NodeStickyLinks-0.2.dist-info/LICENSE
NodeStickyLinks-0.2.dist-info/METADATA
NodeStickyLinks-0.2.dist-info/WHEEL
NodeStickyLinks-0.2.dist-info/top_level.txt
NodeStickyLinks-0.2.dist-info/RECORD
