Metadata-Version: 2.1
Name: NodeStickyLinks
Version: 0.2
Summary: NodeStickyLinks by python
Home-page: https://github.com/SZUVIZ/StickyLinks
Author: Xiangfang Zeng
Author-email: xiangfangzeng15@gmail.com
License: MIT
Platform: UNKNOWN
Classifier: License :: OSI Approved :: MIT License
Classifier: Intended Audience :: Developers
Classifier: Programming Language :: Python :: 3.9 
License-File: LICENSE
Requires-Dist: pycairo >=1.19.1
Requires-Dist: pandas
Requires-Dist: networkx
